pylint_sort_functions/__init__.py
pylint_sort_functions/auto_fix.py
pylint_sort_functions/checker.py
pylint_sort_functions/cli.py
pylint_sort_functions/file_operations.py
pylint_sort_functions/messages.py
pylint_sort_functions/privacy_analyzer.py
pylint_sort_functions/privacy_fixer.py
pylint_sort_functions/privacy_types.py
pylint_sort_functions/py.typed
pylint_sort_functions/test_file_manager.py
pylint_sort_functions/test_file_updater.py
pylint_sort_functions/utils/__init__.py
pylint_sort_functions/utils/ast_analysis.py
pylint_sort_functions/utils/categorization.py
pylint_sort_functions/utils/decorators.py
pylint_sort_functions/utils/file_patterns.py
pylint_sort_functions/utils/privacy.py
pylint_sort_functions/utils/sorting.py
pylint_sort_functions-1.4.0.dist-info/METADATA
pylint_sort_functions-1.4.0.dist-info/WHEEL
pylint_sort_functions-1.4.0.dist-info/entry_points.txt
pylint_sort_functions-1.4.0.dist-info/RECORD
