Metadata-Version: 2.4
Name: pylint-sort-functions
Version: 1.4.0
Summary: Pylint plugin to sort functions in Python code
Author-email: Håkon Hægland <hakon.hagland@gmail.com>
Requires-Python: >=3.11
Requires-Dist: astroid>=3.3.0
Requires-Dist: pylint>=3.3.0
